{
  "id": "strategic-reading",
  "title": "Strategic Reading",
  "descriptionZh": "用于 Strategic Reading 相关任务的 Codex 技能，适合需要对应专业工作流或工具指导时使用。",
  "type": "codex-skill",
  "category": "开发辅助",
  "prerequisites": [],
  "sourceUrl": "https://github.com/garrytan/gbrain/tree/master/skills/strategic-reading",
  "homepage": "https://github.com/garrytan/gbrain",
  "license": "See upstream",
  "author": "garrytan",
  "status": "experimental",
  "updatedAt": "2026-07-15",
  "upstreamCommit": "5008b287e47bf791132eedfebf66bdef11e9398c",
  "upstreamPath": "skills/strategic-reading/SKILL.md",
  "upstreamSha256": "5be656c39c830153ec7c2f328dc8bdeac05c1412b01b3415de6b5b008926e7a2"
}
