{
  "id": "gh-credit-harvest",
  "title": "Gh Credit Harvest",
  "descriptionZh": "用于 Gh Credit Harvest 相关任务的 Codex 技能，适合需要对应专业工作流或工具指导时使用。",
  "type": "codex-skill",
  "category": "开发辅助",
  "prerequisites": [],
  "sourceUrl": "https://github.com/Hmbown/CodeWhale/tree/main/docs/skills/gh-credit-harvest",
  "homepage": "https://github.com/Hmbown/CodeWhale",
  "license": "See upstream",
  "author": "Hmbown",
  "status": "experimental",
  "updatedAt": "2026-07-15",
  "upstreamCommit": "352e86a611fdf3cd8bd27c36d24d482c06a71117",
  "upstreamPath": "docs/skills/gh-credit-harvest/SKILL.md",
  "upstreamSha256": "5977fc88e8b5c52c6e83a3b8f9f24b1556fd1f75f3b7e493fd6e3b689713dd3a"
}
